tests/__init__.py
tests/test_configure.py
tests/test_utils.py
tests/test_wso.py
wso/__init__.py
wso/configure.py
wso/utilities.py
wso/wso.py
wso/system_parameters/countries.json
wso/system_parameters/device_application_status.json
wso/system_parameters/device_models.json
wso/system_parameters/device_ownership.json
wso/system_parameters/locale.json
wso/system_parameters/os_ids.json
wso/system_parameters/platforms.json
wso/system_parameters/timezones.json
wso-1.0.7.dist-info/LICENSE
wso-1.0.7.dist-info/METADATA
wso-1.0.7.dist-info/WHEEL
wso-1.0.7.dist-info/top_level.txt
wso-1.0.7.dist-info/RECORD
