Metadata-Version: 2.1
Name: wso
Version: 1.0.7
Summary: A Library for interacting with WSO UEM
Home-page: https://github.com/rorymurdock/wso
Author: Rory Murdock
Author-email: rory@itmatic.com.au
License: UNKNOWN
Platform: UNKNOWN
Classifier: Development Status :: 5 - Production/Stable
Classifier: License :: OSI Approved :: Apache Software License
Classifier: Operating System :: OS Independent
Requires-Dist: reqrest
Requires-Dist: basic-auth
